swat_em/__init__.py
swat_em/analyse.py
swat_em/config.py
swat_em/datamodel.py
swat_em/dialog_about.py
swat_em/dialog_combination_sniffer.py
swat_em/dialog_genwdg.py
swat_em/dialog_import_winding.py
swat_em/dialog_notes.py
swat_em/dialog_settings.py
swat_em/dialog_winding_layout.py
swat_em/main.py
swat_em/plots.py
swat_em/report.py
swat_em/wdggenerator.py
swat_em/doc/SWAT-EM_manual.pdf
swat_em/template/report.html
swat_em/ui/About.ui
swat_em/ui/CombSniffer.ui
swat_em/ui/CombSnifferSelIndix.ui
swat_em/ui/Factors.ui
swat_em/ui/GenCombinations.ui
swat_em/ui/GenWinding2.ui
swat_em/ui/ImportWinding.ui
swat_em/ui/MachineData.ui
swat_em/ui/MainWindow.ui
swat_em/ui/Notes.ui
swat_em/ui/Settings.ui
swat_em/ui/choose_generator.ui
swat_em/ui/winding_layout.ui
swat_em/ui/bitmaps/splash.png
swat_em/ui/bitmaps/splash.svg
swat_em/ui/icons/MMK.png
swat_em/ui/icons/MMK.svg
swat_em/ui/icons/app_icon.ico
swat_em/ui/icons/app_icon.png
swat_em/ui/icons/app_icon.svg
swat_em/ui/icons/app_icon_create.sh
swat_em/ui/icons/clipboard.png
swat_em/ui/icons/clipboard.svg
swat_em/ui/icons/clone.png
swat_em/ui/icons/clone.svg
swat_em/ui/icons/coil.png
swat_em/ui/icons/coil.svg
swat_em/ui/icons/delete.png
swat_em/ui/icons/delete.svg
swat_em/ui/icons/edit_manually.png
swat_em/ui/icons/edit_manually.svg
swat_em/ui/icons/excel.png
swat_em/ui/icons/excel.svg
swat_em/ui/icons/find.png
swat_em/ui/icons/find.svg
swat_em/ui/icons/find_next.png
swat_em/ui/icons/find_next.svg
swat_em/ui/icons/generator.png
swat_em/ui/icons/generator.svg
swat_em/ui/icons/help.png
swat_em/ui/icons/help.svg
swat_em/ui/icons/html.png
swat_em/ui/icons/html.svg
swat_em/ui/icons/import.png
swat_em/ui/icons/import.svg
swat_em/ui/icons/info.png
swat_em/ui/icons/info.svg
swat_em/ui/icons/layout_polar.png
swat_em/ui/icons/layout_polar.svg
swat_em/ui/icons/new.png
swat_em/ui/icons/new.svg
swat_em/ui/icons/notes.png
swat_em/ui/icons/notes.svg
swat_em/ui/icons/open.png
swat_em/ui/icons/open.svg
swat_em/ui/icons/palette.svg
swat_em-0.6.3.dist-info/LICENSE
swat_em-0.6.3.dist-info/METADATA
swat_em-0.6.3.dist-info/WHEEL
swat_em-0.6.3.dist-info/entry_points.txt
swat_em-0.6.3.dist-info/top_level.txt
swat_em-0.6.3.dist-info/RECORD
