Metadata-Version: 2.1
Name: swat-em
Version: 0.6.3
Summary: Specific Winding Analysing Tool for Electrical Machines
Home-page: https://gitlab.com/martinbaun/swat-em
Author: Martin Baun
Author-email: mar.baun@googlemail.com
License: UNKNOWN
Platform: any
Classifier: Programming Language :: Python :: 3
Classifier: License :: OSI Approved :: MIT License
Classifier: Operating System :: OS Independent
Requires-Dist: PyQt5
Requires-Dist: numpy
Requires-Dist: pyqtgraph
Requires-Dist: xlsxwriter
